AUTHORS.md
LICENSE
README.md
README.rst
setup.cfg
setup.py
django_sage_encrypt.egg-info/PKG-INFO
django_sage_encrypt.egg-info/SOURCES.txt
django_sage_encrypt.egg-info/dependency_links.txt
django_sage_encrypt.egg-info/requires.txt
django_sage_encrypt.egg-info/top_level.txt
sage_encrypt/__init__.py
sage_encrypt/apps.py
sage_encrypt/settings.py
sage_encrypt/collections/__init__.py
sage_encrypt/collections/asymmetric.py
sage_encrypt/collections/symmetric.py
sage_encrypt/fields/__init__.py
sage_encrypt/fields/asymmetric.py
sage_encrypt/fields/symmetric.py
sage_encrypt/management/__init__.py
sage_encrypt/management/commands/__init__.py
sage_encrypt/management/commands/decryptdb.py
sage_encrypt/management/commands/encryptdb.py
sage_encrypt/mixins/__init__.py
sage_encrypt/mixins/cast.py
sage_encrypt/mixins/encrypt.py
sage_encrypt/mixins/query.py
sage_encrypt/mixins/sql.py
sage_encrypt/services/__init__.py
sage_encrypt/services/encrypt.py
sage_encrypt/services/setting.py